styx/__init__.py
styx/backend/__init__.py
styx/backend/python/__init__.py
styx/backend/python/constraints.py
styx/backend/python/core.py
styx/backend/python/documentation.py
styx/backend/python/interface.py
styx/backend/python/lookup.py
styx/backend/python/metadata.py
styx/backend/python/pycodegen/__init__.py
styx/backend/python/pycodegen/core.py
styx/backend/python/pycodegen/scope.py
styx/backend/python/pycodegen/string_case.py
styx/backend/python/pycodegen/utils.py
styx/backend/python/utils.py
styx/frontend/__init__.py
styx/frontend/boutiques/__init__.py
styx/frontend/boutiques/core.py
styx/frontend/boutiques/utils.py
styx/ir/__init__.py
styx/ir/core.py
styx/ir/optimize.py
styx/ir/pretty_print.py
styx/ir/stats.py
styxcompiler-0.1.1.dist-info/LICENSE
styxcompiler-0.1.1.dist-info/METADATA
styxcompiler-0.1.1.dist-info/WHEEL
styxcompiler-0.1.1.dist-info/entry_points.txt
styxcompiler-0.1.1.dist-info/RECORD
