Metadata-Version: 2.1
Name: styxcompiler
Version: 0.1.1
Summary: Boutiques code generator
License: LGPL-2.1
Author: Florian Rupprecht
Author-email: floruppr@gmail.com
Requires-Python: >=3.11,<4.0
Classifier: License :: OSI Approved
Classifier: Programming Language :: Python :: 3
Classifier: Programming Language :: Python :: 3.11
Classifier: Programming Language :: Python :: 3.12
Classifier: Programming Language :: Python :: 3.13
Provides-Extra: docs
Requires-Dist: styxdefs (>=0.3.0,<0.4.0)
